__init__.py
example.py
leaf/__init__.py
leaf/exception.py
leaf/filesystem.py
tests/tests.py
leaf_BasedLabs-0.0.9.dist-info/LICENSE
leaf_BasedLabs-0.0.9.dist-info/METADATA
leaf_BasedLabs-0.0.9.dist-info/WHEEL
leaf_BasedLabs-0.0.9.dist-info/top_level.txt
leaf_BasedLabs-0.0.9.dist-info/RECORD
