Metadata-Version: 2.1
Name: leaf_BasedLabs
Version: 0.0.9
Summary: Leaf is a small (just two .py files) on-demand hierachical filesystem database.
Author-email: Igor Bruev <jaktenstid1@gmail.com>
Project-URL: Homepage, https://github.com/BasedLabs/leaf
Project-URL: Issues, https://github.com/BasedLabs/leaf/issues
Classifier: Programming Language :: Python :: 3
Classifier: License :: OSI Approved :: MIT License
Classifier: Operating System :: OS Independent
Requires-Python: >=3
License-File: LICENSE
